{"pipeline_id": "spipe_3c5c04aa", "checkpoint_id": "0a97c1b1", "timestamp": "2026-05-29T06:36:08.140963+00:00", "watermark": 1780036557.7312746, "window_states": [{"window_key": "key_0|1780036565-1780036570", "window_start": 1780036565.0, "window_end": 1780036570.0, "event_count": 7, "aggregations": {"count": 7}, "last_event_time": 1780036567.7312746, "is_closed": false}, {"window_key": "key_1|1780036565-1780036570", "window_start": 1780036565.0, "window_end": 1780036570.0, "event_count": 13, "aggregations": {"count": 13}, "last_event_time": 1780036567.717024, "is_closed": false}], "source_offsets": {"event_count": 40, "start_time": 1780036567.7325087}, "metrics_snapshot": {"pipeline_id": "spipe_3c5c04aa", "status": "stopped", "events_in": 20, "events_out": 0, "events_late": 0, "events_dropped": 0, "events_per_second": 49.2, "watermark_position": 0.0, "active_windows": 0, "closed_windows": 0, "last_checkpoint_at": null, "uptime_seconds": 0.0, "backpressure": null, "errors": []}}