{"pipeline_id": "spipe_8c26e58a", "checkpoint_id": "32328e53", "timestamp": "2026-05-30T03:26:31.955589+00:00", "watermark": 1780111580.7948358, "window_states": [{"window_key": "key_1|1780111590-1780111595", "window_start": 1780111590.0, "window_end": 1780111595.0, "event_count": 18, "aggregations": {"count": 18}, "last_event_time": 1780111590.7532923, "is_closed": false}, {"window_key": "key_1|1780111585-1780111590", "window_start": 1780111585.0, "window_end": 1780111590.0, "event_count": 3, "aggregations": {"count": 3}, "last_event_time": 1780111589.9755166, "is_closed": false}, {"window_key": "key_0|1780111590-1780111595", "window_start": 1780111590.0, "window_end": 1780111595.0, "event_count": 17, "aggregations": {"count": 17}, "last_event_time": 1780111590.7948358, "is_closed": false}, {"window_key": "key_0|1780111585-1780111590", "window_start": 1780111585.0, "window_end": 1780111590.0, "event_count": 1, "aggregations": {"count": 1}, "last_event_time": 1780111589.9463296, "is_closed": false}], "source_offsets": {"event_count": 60, "start_time": 1780111590.4157376}, "metrics_snapshot": {"pipeline_id": "spipe_8c26e58a", "status": "running", "events_in": 40, "events_out": 0, "events_late": 1, "events_dropped": 0, "events_per_second": 32.2, "watermark_position": 1780111580.7948358, "active_windows": 4, "closed_windows": 0, "last_checkpoint_at": "2026-05-30T03:26:30.831432+00:00", "uptime_seconds": 1.5, "backpressure": {"buffer_depth": 0, "buffer_utilization": 0.0, "is_pressured": false, "dropped_count": 0, "total_pressure_seconds": 0.0, "strategy": "block"}, "errors": []}}