{"pipeline_id": "spipe_d7e4edd1", "checkpoint_id": "d5e6527f", "timestamp": "2026-06-01T10:59:35.709449+00:00", "watermark": 1780311565.0688415, "window_states": [{"window_key": "key_1|1780311570-1780311575", "window_start": 1780311570.0, "window_end": 1780311575.0, "event_count": 17, "aggregations": {"count": 17}, "last_event_time": 1780311574.9845822, "is_closed": false}, {"window_key": "key_0|1780311570-1780311575", "window_start": 1780311570.0, "window_end": 1780311575.0, "event_count": 20, "aggregations": {"count": 20}, "last_event_time": 1780311574.998352, "is_closed": false}, {"window_key": "key_0|1780311575-1780311580", "window_start": 1780311575.0, "window_end": 1780311580.0, "event_count": 2, "aggregations": {"count": 2}, "last_event_time": 1780311575.0570848, "is_closed": false}, {"window_key": "key_1|1780311575-1780311580", "window_start": 1780311575.0, "window_end": 1780311580.0, "event_count": 1, "aggregations": {"count": 1}, "last_event_time": 1780311575.0688415, "is_closed": false}], "source_offsets": {"event_count": 60, "start_time": 1780311574.6977234}, "metrics_snapshot": {"pipeline_id": "spipe_d7e4edd1", "status": "running", "events_in": 40, "events_out": 0, "events_late": 0, "events_dropped": 0, "events_per_second": 48.5, "watermark_position": 1780311565.0688415, "active_windows": 4, "closed_windows": 0, "last_checkpoint_at": "2026-06-01T10:59:35.114375+00:00", "uptime_seconds": 1.0, "backpressure": {"buffer_depth": 0, "buffer_utilization": 0.0, "is_pressured": false, "dropped_count": 0, "total_pressure_seconds": 0.0, "strategy": "block"}, "errors": []}}